odoo/addons/openupgrade_framework/README.rst
odoo/addons/openupgrade_framework/__init__.py
odoo/addons/openupgrade_framework/__manifest__.py
odoo/addons/openupgrade_framework/odoo_patch/__init__.py
odoo/addons/openupgrade_framework/odoo_patch/odoo/__init__.py
odoo/addons/openupgrade_framework/odoo_patch/odoo/api.py
odoo/addons/openupgrade_framework/odoo_patch/odoo/models.py
odoo/addons/openupgrade_framework/odoo_patch/odoo/addons/__init__.py
odoo/addons/openupgrade_framework/odoo_patch/odoo/addons/base/__init__.py
odoo/addons/openupgrade_framework/odoo_patch/odoo/addons/base/models/__init__.py
odoo/addons/openupgrade_framework/odoo_patch/odoo/addons/base/models/ir_model.py
odoo/addons/openupgrade_framework/odoo_patch/odoo/addons/base/models/ir_ui_view.py
odoo/addons/openupgrade_framework/odoo_patch/odoo/modules/__init__.py
odoo/addons/openupgrade_framework/odoo_patch/odoo/modules/graph.py
odoo/addons/openupgrade_framework/odoo_patch/odoo/modules/migration.py
odoo/addons/openupgrade_framework/readme/CONFIGURE.rst
odoo/addons/openupgrade_framework/readme/CONTRIBUTORS.rst
odoo/addons/openupgrade_framework/readme/CREDITS.rst
odoo/addons/openupgrade_framework/readme/DESCRIPTION.rst
odoo/addons/openupgrade_framework/readme/DEVELOP.rst
odoo/addons/openupgrade_framework/readme/INSTALL.rst
odoo/addons/openupgrade_framework/static/description/banner.png
odoo/addons/openupgrade_framework/static/description/icon.png
odoo/addons/openupgrade_framework/static/description/index.html
odoo14_addon_openupgrade_framework-14.0.1.0.1.dev22.dist-info/METADATA
odoo14_addon_openupgrade_framework-14.0.1.0.1.dev22.dist-info/WHEEL
odoo14_addon_openupgrade_framework-14.0.1.0.1.dev22.dist-info/top_level.txt
odoo14_addon_openupgrade_framework-14.0.1.0.1.dev22.dist-info/RECORD
