Metadata-Version: 2.1
Name: odoo14-addon-openupgrade-framework
Version: 14.0.1.0.1.dev22
Summary: Module to integrate in the server_wide_modules option to make upgrades between two major revisions.
Home-page: https://github.com/OCA/openupgrade
Author: Odoo Community Association (OCA), Therp BV, Opener B.V., GRAP
Author-email: support@odoo-community.org
License: AGPL-3
Platform: UNKNOWN
Classifier: Programming Language :: Python
Classifier: Framework :: Odoo
Classifier: Framework :: Odoo :: 14.0
Classifier: License :: OSI Approved :: GNU Affero General Public License v3
Requires-Python: >=3.6
Requires-Dist: odoo <14.1dev,>=14.0a
Requires-Dist: openupgradelib
